MANIFEST.in
README.md
setup.py
pymangle/__init__.py
pymangle/_mangle.c
pymangle/cap.c
pymangle/cap.h
pymangle/defs.h
pymangle/mangle.c
pymangle/mangle.h
pymangle/mangle.py
pymangle/pixel.c
pymangle/pixel.h
pymangle/point.c
pymangle/point.h
pymangle/polygon.c
pymangle/polygon.h
pymangle/rand.c
pymangle/rand.h
pymangle/stack.c
pymangle/stack.h
pymangle/version.py
pymangle.egg-info/PKG-INFO
pymangle.egg-info/SOURCES.txt
pymangle.egg-info/dependency_links.txt
pymangle.egg-info/requires.txt
pymangle.egg-info/top_level.txt
tests/test_pymangle.py