Metadata-Version: 2.1
Name: pymangle
Version: 0.9.3
Summary: A python code to read and work with Mangle masks.
License: GPL
Requires-Dist: numpy
